LICENSE
MANIFEST.in
README.md
install.json
package.json
pyproject.toml
setup.py
tsconfig.json
yarn.lock
jupyter-config/jupyterlab_s3_browser.json
jupyterlab_s3_browser_yq/__init__.py
jupyterlab_s3_browser_yq/_version.py
jupyterlab_s3_browser_yq/handlers.py
jupyterlab_s3_browser_yq.egg-info/PKG-INFO
jupyterlab_s3_browser_yq.egg-info/SOURCES.txt
jupyterlab_s3_browser_yq.egg-info/dependency_links.txt
jupyterlab_s3_browser_yq.egg-info/not-zip-safe
jupyterlab_s3_browser_yq.egg-info/requires.txt
jupyterlab_s3_browser_yq.egg-info/top_level.txt
jupyterlab_s3_browser_yq/labextension/package.json
jupyterlab_s3_browser_yq/labextension/static/268.c468775986f6fa82a3a1.js
jupyterlab_s3_browser_yq/labextension/static/534.55a11ce6277c0ac4f838.js
jupyterlab_s3_browser_yq/labextension/static/742.6e352808ed7772df86f7.js
jupyterlab_s3_browser_yq/labextension/static/remoteEntry.6142ab1dac279d74c672.js
jupyterlab_s3_browser_yq/labextension/static/style.js
jupyterlab_s3_browser_yq/tests/__init__.py
jupyterlab_s3_browser_yq/tests/test_auth.py
jupyterlab_s3_browser_yq/tests/test_get_s3.py
src/browser.ts
src/contents.ts
src/index.ts
style/base.css
style/bucket-dark.svg
style/bucket-light.svg
style/index.css
style/index.js