Metadata-Version: 2.1
Name: jupyterlab-s3-browser-yq
Version: 0.10.2
Summary: JupyterLab extension for browsing S3-compatible object storage
Home-page: https://github.com/IBM/jupyterlab_s3_browser
Author: James Reeve
License: Apache-2.0
Keywords: Jupyter,JupyterLab,JupyterLab3,S3
Platform: Linux
Platform: Mac OS X
Platform: Windows
Classifier: Intended Audience :: Developers
Classifier: Intended Audience :: Education
Classifier: Intended Audience :: Science/Research
Classifier: License :: OSI Approved :: Apache Software License
Classifier: Programming Language :: Python
Classifier: Programming Language :: Python :: 3
Classifier: Framework :: Jupyter
Requires-Python: >=3.6
Provides-Extra: dev
